tilecloud_chain/CONFIG.md
tilecloud_chain/HOST_LIMIT.md
tilecloud_chain/USAGE.rst
tilecloud_chain/__init__.py
tilecloud_chain/configuration.py
tilecloud_chain/controller.py
tilecloud_chain/copy_.py
tilecloud_chain/cost.py
tilecloud_chain/database_logger.py
tilecloud_chain/expiretiles.py
tilecloud_chain/filter/__init__.py
tilecloud_chain/filter/error.py
tilecloud_chain/format.py
tilecloud_chain/generate.py
tilecloud_chain/host-limit-schema.json
tilecloud_chain/host_limit.py
tilecloud_chain/internal_mapcache.py
tilecloud_chain/multitilestore.py
tilecloud_chain/py.typed
tilecloud_chain/schema.json
tilecloud_chain/security.py
tilecloud_chain/server.py
tilecloud_chain/static/favicon-16x16.png
tilecloud_chain/static/favicon-32x32.png
tilecloud_chain/store/__init__.py
tilecloud_chain/store/azure_storage_blob.py
tilecloud_chain/store/mapnik_.py
tilecloud_chain/store/postgresql.py
tilecloud_chain/store/url.py
tilecloud_chain/templates/admin_index.html
tilecloud_chain/templates/openlayers.html
tilecloud_chain/tests/__init__.py
tilecloud_chain/tests/apache.conf
tilecloud_chain/tests/create_test_data.sh
tilecloud_chain/tests/index.expected.png
tilecloud_chain/tests/mapfile/circle.svg
tilecloud_chain/tests/mapfile/mapfile.map
tilecloud_chain/tests/mapfile/test.mapnik
tilecloud_chain/tests/not-login.expected.png
tilecloud_chain/tests/test.expected.png
tilecloud_chain/tests/test_config.py
tilecloud_chain/tests/test_controller.py
tilecloud_chain/tests/test_copy.py
tilecloud_chain/tests/test_cost.py
tilecloud_chain/tests/test_error.py
tilecloud_chain/tests/test_expiretiles.py
tilecloud_chain/tests/test_generate.py
tilecloud_chain/tests/test_multi_grid.py
tilecloud_chain/tests/test_postgresql.py
tilecloud_chain/tests/test_serve.py
tilecloud_chain/tests/test_ui.py
tilecloud_chain/tests/tilegeneration/deploy.cfg
tilecloud_chain/tests/tilegeneration/hooks/post-create-database
tilecloud_chain/tests/tilegeneration/hooks/post-restore-database
tilecloud_chain-1.23.1.dist-info/LICENSE
tilecloud_chain-1.23.1.dist-info/METADATA
tilecloud_chain-1.23.1.dist-info/WHEEL
tilecloud_chain-1.23.1.dist-info/entry_points.txt
tilecloud_chain-1.23.1.dist-info/RECORD
