Metadata-Version: 2.3
Name: tilecloud-chain
Version: 1.23.1
Summary: Tools to generate tiles from WMS or Mapnik, to S3, Berkeley DB, MBTiles, or local filesystem in WMTS layout using Amazon cloud services.
License: BSD-2-Clause
Keywords: gis,tilecloud,chain
Author: Camptocamp
Author-email: info@camptocamp.com
Requires-Python: >=3.10
Classifier: Development Status :: 5 - Production/Stable
Classifier: Environment :: Web Environment
Classifier: Framework :: Pyramid
Classifier: Intended Audience :: Other Audience
Classifier: License :: OSI Approved :: BSD License
Classifier: Operating System :: OS Independent
Classifier: Programming Language :: Python
Classifier: Programming Language :: Python :: 3
Classifier: Programming Language :: Python :: 3.10
Classifier: Programming Language :: Python :: 3.11
Classifier: Programming Language :: Python :: 3.12
Classifier: Programming Language :: Python :: 3.13
Classifier: Topic :: Scientific/Engineering :: GIS
Classifier: Typing :: Typed
Requires-Dist: Jinja2
Requires-Dist: Paste
Requires-Dist: PyYAML
Requires-Dist: Shapely
Requires-Dist: aiofiles
Requires-Dist: aiohttp
Requires-Dist: asyncpg
Requires-Dist: azure-storage-blob
Requires-Dist: c2cwsgiutils[broadcast,debug,oauth2,standard]
Requires-Dist: certifi
Requires-Dist: jsonschema
Requires-Dist: jsonschema-validator-new
Requires-Dist: nest-asyncio
Requires-Dist: psutil
Requires-Dist: psycopg[binary]
Requires-Dist: pyproj
Requires-Dist: pyramid
Requires-Dist: pyramid-mako
Requires-Dist: pytest-asyncio
Requires-Dist: python-dateutil
Requires-Dist: sqlalchemy[asyncio]
Requires-Dist: tilecloud[aws,azure,redis,wsgi]
Requires-Dist: waitress
Project-URL: Bug Tracker, https://github.com/camptocamp/tilecloud-chain/issues
Project-URL: Repository, https://github.com/camptocamp/tilecloud-chain
